topsis/__init__.py
topsis/__main__.py
Topsis_Ikshul_101903458-2.0.0.dist-info/LICENSE.txt
Topsis_Ikshul_101903458-2.0.0.dist-info/METADATA
Topsis_Ikshul_101903458-2.0.0.dist-info/WHEEL
Topsis_Ikshul_101903458-2.0.0.dist-info/entry_points.txt
Topsis_Ikshul_101903458-2.0.0.dist-info/top_level.txt
Topsis_Ikshul_101903458-2.0.0.dist-info/RECORD
