Metadata-Version: 2.1
Name: Topsis-Ikshul-101903458
Version: 2.0.0
Summary: A package -> Calculates Topsis Score and Rank them accordingly
Home-page: https://github.com/IkshulDureja/Topsis-Ikshul-101903458
Author: Ikshul Dureja
Author-email: ikshuldureja130@gmail.com
License: MIT
Platform: UNKNOWN
Classifier: Programming Language :: Python :: 3
Classifier: License :: OSI Approved :: MIT License
Classifier: Operating System :: OS Independent
Requires-Dist: pandas
